Metadata-Version: 1.0
Name: saman-distributions
Version: 0.1
Summary: Gaussian distributions class
Home-page: UNKNOWN
Author: Saman
Author-email: UNKNOWN
License: UNKNOWN
Platform: UNKNOWN
